{
  "name": "beamer",
  "files": [
    {
      "path": "/texlive/texmf-dist/doc/latex/beamer",
      "name": "AUTHORS.md",
      "start": 0,
      "end": 1642
    },
    {
      "path": "/texlive/texmf-dist/doc/latex/beamer",
      "name": "beamercolorthemeexample.tex",
      "start": 1642,
      "end": 2986
    },
    {
      "path": "/texlive/texmf-dist/doc/latex/beamer",
      "name": "beamerexample-conference-talk.pdf",
      "start": 2986,
      "end": 257188
    },
    {
      "path": "/texlive/texmf-dist/doc/latex/beamer",
      "name": "beamerexample-lecture-beamer-version.pdf",
      "start": 257188,
      "end": 687770
    },
    {
      "path": "/texlive/texmf-dist/doc/latex/beamer",
      "name": "beamerexample-lecture-print-version.pdf",
      "start": 687770,
      "end": 1054927
    },
    {
      "path": "/texlive/texmf-dist/doc/latex/beamer",
      "name": "beamerfontthemeexample.tex",
      "start": 1054927,
      "end": 1055407
    },
    {
      "path": "/texlive/texmf-dist/doc/latex/beamer",
      "name": "beamerinnerthemeexample.tex",
      "start": 1055407,
      "end": 1056113
    },
    {
      "path": "/texlive/texmf-dist/doc/latex/beamer",
      "name": "beamerlogo.pdf",
      "start": 1056113,
      "end": 1058202
    },
    {
      "path": "/texlive/texmf-dist/doc/latex/beamer",
      "name": "beamerouterthemeexample.tex",
      "start": 1058202,
      "end": 1058656
    },
    {
      "path": "/texlive/texmf-dist/doc/latex/beamer",
      "name": "beamerthemeexample.tex",
      "start": 1058656,
      "end": 1059132
    },
    {
      "path": "/texlive/texmf-dist/doc/latex/beamer",
      "name": "beamerthemeexamplebase.tex",
      "start": 1059132,
      "end": 1060664
    },
    {
      "path": "/texlive/texmf-dist/doc/latex/beamer",
      "name": "beamerug-animations.tex",
      "start": 1060664,
      "end": 1096362
    },
    {
      "path": "/texlive/texmf-dist/doc/latex/beamer",
      "name": "beamerug-color.tex",
      "start": 1096362,
      "end": 1132708
    },
    {
      "path": "/texlive/texmf-dist/doc/latex/beamer",
      "name": "beamerug-compatibility.tex",
      "start": 1132708,
      "end": 1145339
    },
    {
      "path": "/texlive/texmf-dist/doc/latex/beamer",
      "name": "beamerug-elements.tex",
      "start": 1145339,
      "end": 1179085
    },
    {
      "path": "/texlive/texmf-dist/doc/latex/beamer",
      "name": "beamerug-emulation.tex",
      "start": 1179085,
      "end": 1211728
    },
    {
      "path": "/texlive/texmf-dist/doc/latex/beamer",
      "name": "beamerug-fonts.tex",
      "start": 1211728,
      "end": 1233182
    },
    {
      "path": "/texlive/texmf-dist/doc/latex/beamer",
      "name": "beamerug-frames.tex",
      "start": 1233182,
      "end": 1310607
    },
    {
      "path": "/texlive/texmf-dist/doc/latex/beamer",
      "name": "beamerug-globalstructure.tex",
      "start": 1310607,
      "end": 1350706
    },
    {
      "path": "/texlive/texmf-dist/doc/latex/beamer",
      "name": "beamerug-graphics.tex",
      "start": 1350706,
      "end": 1359830
    },
    {
      "path": "/texlive/texmf-dist/doc/latex/beamer",
      "name": "beamerug-guidelines.tex",
      "start": 1359830,
      "end": 1401131
    },
    {
      "path": "/texlive/texmf-dist/doc/latex/beamer",
      "name": "beamerug-installation.tex",
      "start": 1401131,
      "end": 1407181
    },
    {
      "path": "/texlive/texmf-dist/doc/latex/beamer",
      "name": "beamerug-interaction.tex",
      "start": 1407181,
      "end": 1423686
    },
    {
      "path": "/texlive/texmf-dist/doc/latex/beamer",
      "name": "beamerug-introduction.tex",
      "start": 1423686,
      "end": 1438650
    },
    {
      "path": "/texlive/texmf-dist/doc/latex/beamer",
      "name": "beamerug-license.tex",
      "start": 1438650,
      "end": 1479360
    },
    {
      "path": "/texlive/texmf-dist/doc/latex/beamer",
      "name": "beamerug-localstructure.tex",
      "start": 1479360,
      "end": 1544192
    },
    {
      "path": "/texlive/texmf-dist/doc/latex/beamer",
      "name": "beamerug-macros.tex",
      "start": 1544192,
      "end": 1556647
    },
    {
      "path": "/texlive/texmf-dist/doc/latex/beamer",
      "name": "beamerug-nonpresentation.tex",
      "start": 1556647,
      "end": 1578894
    },
    {
      "path": "/texlive/texmf-dist/doc/latex/beamer",
      "name": "beamerug-notes.tex",
      "start": 1578894,
      "end": 1589843
    },
    {
      "path": "/texlive/texmf-dist/doc/latex/beamer",
      "name": "beamerug-overlays.tex",
      "start": 1589843,
      "end": 1630765
    },
    {
      "path": "/texlive/texmf-dist/doc/latex/beamer",
      "name": "beamerug-solutions.tex",
      "start": 1630765,
      "end": 1633576
    },
    {
      "path": "/texlive/texmf-dist/doc/latex/beamer",
      "name": "beamerug-themes.tex",
      "start": 1633576,
      "end": 1652098
    },
    {
      "path": "/texlive/texmf-dist/doc/latex/beamer",
      "name": "beamerug-transparencies.tex",
      "start": 1652098,
      "end": 1656461
    },
    {
      "path": "/texlive/texmf-dist/doc/latex/beamer",
      "name": "beamerug-tricks.tex",
      "start": 1656461,
      "end": 1664768
    },
    {
      "path": "/texlive/texmf-dist/doc/latex/beamer",
      "name": "beamerug-tutorial.tex",
      "start": 1664768,
      "end": 1689120
    },
    {
      "path": "/texlive/texmf-dist/doc/latex/beamer",
      "name": "beamerug-twoscreens.tex",
      "start": 1689120,
      "end": 1697146
    },
    {
      "path": "/texlive/texmf-dist/doc/latex/beamer",
      "name": "beamerug-workflow.tex",
      "start": 1697146,
      "end": 1709421
    },
    {
      "path": "/texlive/texmf-dist/doc/latex/beamer",
      "name": "beameruserguide.pdf",
      "start": 1709421,
      "end": 3845567
    },
    {
      "path": "/texlive/texmf-dist/doc/latex/beamer",
      "name": "beameruserguide.tex",
      "start": 3845567,
      "end": 3854285
    },
    {
      "path": "/texlive/texmf-dist/doc/latex/beamer",
      "name": "CHANGELOG.md",
      "start": 3854285,
      "end": 3866189
    },
    {
      "path": "/texlive/texmf-dist/doc/latex/beamer/emulation-examples",
      "name": "beamerexample-foils.tex",
      "start": 3866189,
      "end": 3867183
    },
    {
      "path": "/texlive/texmf-dist/doc/latex/beamer/emulation-examples",
      "name": "beamerexample-prosper.tex",
      "start": 3867183,
      "end": 3869020
    },
    {
      "path": "/texlive/texmf-dist/doc/latex/beamer/emulation-examples",
      "name": "beamerexample-seminar.tex",
      "start": 3869020,
      "end": 3881500
    },
    {
      "path": "/texlive/texmf-dist/doc/latex/beamer/emulation-examples",
      "name": "beamerexample-texpower.tex",
      "start": 3881500,
      "end": 3891730
    },
    {
      "path": "/texlive/texmf-dist/doc/latex/beamer/examples/a-conference-talk",
      "name": "beamerexample-conference-talk.tex",
      "start": 3891730,
      "end": 3912471
    },
    {
      "path": "/texlive/texmf-dist/doc/latex/beamer/examples/a-lecture",
      "name": "beamerexample-lecture-beamer-version.tex",
      "start": 3912471,
      "end": 3912803
    },
    {
      "path": "/texlive/texmf-dist/doc/latex/beamer/examples/a-lecture",
      "name": "beamerexample-lecture-body.tex",
      "start": 3912803,
      "end": 3932094
    },
    {
      "path": "/texlive/texmf-dist/doc/latex/beamer/examples/a-lecture",
      "name": "beamerexample-lecture-logo.pdf",
      "start": 3932094,
      "end": 3964917
    },
    {
      "path": "/texlive/texmf-dist/doc/latex/beamer/examples/a-lecture",
      "name": "beamerexample-lecture-pic1.jpg",
      "start": 3964917,
      "end": 4001750
    },
    {
      "path": "/texlive/texmf-dist/doc/latex/beamer/examples/a-lecture",
      "name": "beamerexample-lecture-pic2.jpg",
      "start": 4001750,
      "end": 4006040
    },
    {
      "path": "/texlive/texmf-dist/doc/latex/beamer/examples/a-lecture",
      "name": "beamerexample-lecture-pic3.jpg",
      "start": 4006040,
      "end": 4046060
    },
    {
      "path": "/texlive/texmf-dist/doc/latex/beamer/examples/a-lecture",
      "name": "beamerexample-lecture-pic4.jpg",
      "start": 4046060,
      "end": 4073850
    },
    {
      "path": "/texlive/texmf-dist/doc/latex/beamer/examples/a-lecture",
      "name": "beamerexample-lecture-pic5.jpg",
      "start": 4073850,
      "end": 4122861
    },
    {
      "path": "/texlive/texmf-dist/doc/latex/beamer/examples/a-lecture",
      "name": "beamerexample-lecture-pic6.jpg",
      "start": 4122861,
      "end": 4150640
    },
    {
      "path": "/texlive/texmf-dist/doc/latex/beamer/examples/a-lecture",
      "name": "beamerexample-lecture-print-version.tex",
      "start": 4150640,
      "end": 4151010
    },
    {
      "path": "/texlive/texmf-dist/doc/latex/beamer/examples/a-lecture",
      "name": "beamerexample-lecture-style.tex",
      "start": 4151010,
      "end": 4156514
    },
    {
      "path": "/texlive/texmf-dist/doc/latex/beamer",
      "name": "LICENSE.md",
      "start": 4156514,
      "end": 4157867
    },
    {
      "path": "/texlive/texmf-dist/doc/latex/beamer/licenses",
      "name": "fdl.txt",
      "start": 4157867,
      "end": 4180831
    },
    {
      "path": "/texlive/texmf-dist/doc/latex/beamer/licenses",
      "name": "gpl-2.0.txt",
      "start": 4180831,
      "end": 4198923
    },
    {
      "path": "/texlive/texmf-dist/doc/latex/beamer/licenses",
      "name": "lppl-1-3c.txt",
      "start": 4198923,
      "end": 4218029
    },
    {
      "path": "/texlive/texmf-dist/doc/latex/beamer/licenses",
      "name": "manifest-code.txt",
      "start": 4218029,
      "end": 4221482
    },
    {
      "path": "/texlive/texmf-dist/doc/latex/beamer/licenses",
      "name": "manifest-documentation.txt",
      "start": 4221482,
      "end": 4223527
    },
    {
      "path": "/texlive/texmf-dist/doc/latex/beamer",
      "name": "README.md",
      "start": 4223527,
      "end": 4224638
    },
    {
      "path": "/texlive/texmf-dist/doc/latex/beamer/solutions/conference-talks",
      "name": "conference-ornate-20min.de.tex",
      "start": 4224638,
      "end": 4232196
    },
    {
      "path": "/texlive/texmf-dist/doc/latex/beamer/solutions/conference-talks",
      "name": "conference-ornate-20min.en.tex",
      "start": 4232196,
      "end": 4239054
    },
    {
      "path": "/texlive/texmf-dist/doc/latex/beamer/solutions/conference-talks",
      "name": "conference-ornate-20min.fr.tex",
      "start": 4239054,
      "end": 4247354
    },
    {
      "path": "/texlive/texmf-dist/doc/latex/beamer/solutions/generic-talks",
      "name": "generic-ornate-15min-45min.de.tex",
      "start": 4247354,
      "end": 4252846
    },
    {
      "path": "/texlive/texmf-dist/doc/latex/beamer/solutions/generic-talks",
      "name": "generic-ornate-15min-45min.en.tex",
      "start": 4252846,
      "end": 4257919
    },
    {
      "path": "/texlive/texmf-dist/doc/latex/beamer/solutions/generic-talks",
      "name": "generic-ornate-15min-45min.fr.tex",
      "start": 4257919,
      "end": 4263958
    },
    {
      "path": "/texlive/texmf-dist/doc/latex/beamer/solutions/short-talks",
      "name": "speaker_introduction-ornate-2min.de.tex",
      "start": 4263958,
      "end": 4266919
    },
    {
      "path": "/texlive/texmf-dist/doc/latex/beamer/solutions/short-talks",
      "name": "speaker_introduction-ornate-2min.en.tex",
      "start": 4266919,
      "end": 4269546
    },
    {
      "path": "/texlive/texmf-dist/doc/latex/beamer/solutions/short-talks",
      "name": "speaker_introduction-ornate-2min.fr.tex",
      "start": 4269546,
      "end": 4272618
    },
    {
      "path": "/texlive/texmf-dist/tex/latex/beamer",
      "name": "beamer.cls",
      "start": 4272618,
      "end": 4285130
    },
    {
      "path": "/texlive/texmf-dist/tex/latex/beamer",
      "name": "beamerarticle.sty",
      "start": 4285130,
      "end": 4286790
    },
    {
      "path": "/texlive/texmf-dist/tex/latex/beamer",
      "name": "beamerbasearticle.sty",
      "start": 4286790,
      "end": 4290074
    },
    {
      "path": "/texlive/texmf-dist/tex/latex/beamer",
      "name": "beamerbaseauxtemplates.sty",
      "start": 4290074,
      "end": 4314904
    },
    {
      "path": "/texlive/texmf-dist/tex/latex/beamer",
      "name": "beamerbaseboxes.sty",
      "start": 4314904,
      "end": 4323642
    },
    {
      "path": "/texlive/texmf-dist/tex/latex/beamer",
      "name": "beamerbasecolor.sty",
      "start": 4323642,
      "end": 4336876
    },
    {
      "path": "/texlive/texmf-dist/tex/latex/beamer",
      "name": "beamerbasecompatibility.sty",
      "start": 4336876,
      "end": 4364552
    },
    {
      "path": "/texlive/texmf-dist/tex/latex/beamer",
      "name": "beamerbasedecode.sty",
      "start": 4364552,
      "end": 4373949
    },
    {
      "path": "/texlive/texmf-dist/tex/latex/beamer",
      "name": "beamerbasefont.sty",
      "start": 4373949,
      "end": 4387634
    },
    {
      "path": "/texlive/texmf-dist/tex/latex/beamer",
      "name": "beamerbaseframe.sty",
      "start": 4387634,
      "end": 4412948
    },
    {
      "path": "/texlive/texmf-dist/tex/latex/beamer",
      "name": "beamerbaseframecomponents.sty",
      "start": 4412948,
      "end": 4425537
    },
    {
      "path": "/texlive/texmf-dist/tex/latex/beamer",
      "name": "beamerbaseframesize.sty",
      "start": 4425537,
      "end": 4434551
    },
    {
      "path": "/texlive/texmf-dist/tex/latex/beamer",
      "name": "beamerbaselocalstructure.sty",
      "start": 4434551,
      "end": 4452696
    },
    {
      "path": "/texlive/texmf-dist/tex/latex/beamer",
      "name": "beamerbasemisc.sty",
      "start": 4452696,
      "end": 4460999
    },
    {
      "path": "/texlive/texmf-dist/tex/latex/beamer",
      "name": "beamerbasemodes.sty",
      "start": 4460999,
      "end": 4468951
    },
    {
      "path": "/texlive/texmf-dist/tex/latex/beamer",
      "name": "beamerbasenavigation.sty",
      "start": 4468951,
      "end": 4490567
    },
    {
      "path": "/texlive/texmf-dist/tex/latex/beamer",
      "name": "beamerbasenavigationsymbols.tex",
      "start": 4490567,
      "end": 4498704
    },
    {
      "path": "/texlive/texmf-dist/tex/latex/beamer",
      "name": "beamerbasenotes.sty",
      "start": 4498704,
      "end": 4504456
    },
    {
      "path": "/texlive/texmf-dist/tex/latex/beamer",
      "name": "beamerbaseoptions.sty",
      "start": 4504456,
      "end": 4506199
    },
    {
      "path": "/texlive/texmf-dist/tex/latex/beamer",
      "name": "beamerbaseoverlay.sty",
      "start": 4506199,
      "end": 4534958
    },
    {
      "path": "/texlive/texmf-dist/tex/latex/beamer",
      "name": "beamerbaserequires.sty",
      "start": 4534958,
      "end": 4536541
    },
    {
      "path": "/texlive/texmf-dist/tex/latex/beamer",
      "name": "beamerbasesection.sty",
      "start": 4536541,
      "end": 4550383
    },
    {
      "path": "/texlive/texmf-dist/tex/latex/beamer",
      "name": "beamerbasetemplates.sty",
      "start": 4550383,
      "end": 4556126
    },
    {
      "path": "/texlive/texmf-dist/tex/latex/beamer",
      "name": "beamerbasethemes.sty",
      "start": 4556126,
      "end": 4557256
    },
    {
      "path": "/texlive/texmf-dist/tex/latex/beamer",
      "name": "beamerbasetheorems.sty",
      "start": 4557256,
      "end": 4561795
    },
    {
      "path": "/texlive/texmf-dist/tex/latex/beamer",
      "name": "beamerbasetitle.sty",
      "start": 4561795,
      "end": 4567129
    },
    {
      "path": "/texlive/texmf-dist/tex/latex/beamer",
      "name": "beamerbasetoc.sty",
      "start": 4567129,
      "end": 4574924
    },
    {
      "path": "/texlive/texmf-dist/tex/latex/beamer",
      "name": "beamerbasetranslator.sty",
      "start": 4574924,
      "end": 4575551
    },
    {
      "path": "/texlive/texmf-dist/tex/latex/beamer",
      "name": "beamerbasetwoscreens.sty",
      "start": 4575551,
      "end": 4577399
    },
    {
      "path": "/texlive/texmf-dist/tex/latex/beamer",
      "name": "beamerbaseverbatim.sty",
      "start": 4577399,
      "end": 4581415
    },
    {
      "path": "/texlive/texmf-dist/tex/latex/beamer",
      "name": "beamercolorthemealbatross.sty",
      "start": 4581415,
      "end": 4583546
    },
    {
      "path": "/texlive/texmf-dist/tex/latex/beamer",
      "name": "beamercolorthemebeaver.sty",
      "start": 4583546,
      "end": 4584845
    },
    {
      "path": "/texlive/texmf-dist/tex/latex/beamer",
      "name": "beamercolorthemebeetle.sty",
      "start": 4584845,
      "end": 4586404
    },
    {
      "path": "/texlive/texmf-dist/tex/latex/beamer",
      "name": "beamercolorthemecrane.sty",
      "start": 4586404,
      "end": 4588010
    },
    {
      "path": "/texlive/texmf-dist/tex/latex/beamer",
      "name": "beamercolorthemedefault.sty",
      "start": 4588010,
      "end": 4595212
    },
    {
      "path": "/texlive/texmf-dist/tex/latex/beamer",
      "name": "beamercolorthemedolphin.sty",
      "start": 4595212,
      "end": 4596252
    },
    {
      "path": "/texlive/texmf-dist/tex/latex/beamer",
      "name": "beamercolorthemedove.sty",
      "start": 4596252,
      "end": 4597893
    },
    {
      "path": "/texlive/texmf-dist/tex/latex/beamer",
      "name": "beamercolorthemefly.sty",
      "start": 4597893,
      "end": 4599251
    },
    {
      "path": "/texlive/texmf-dist/tex/latex/beamer",
      "name": "beamercolorthemelily.sty",
      "start": 4599251,
      "end": 4599823
    },
    {
      "path": "/texlive/texmf-dist/tex/latex/beamer",
      "name": "beamercolorthememonarca.sty",
      "start": 4599823,
      "end": 4602136
    },
    {
      "path": "/texlive/texmf-dist/tex/latex/beamer",
      "name": "beamercolorthemeorchid.sty",
      "start": 4602136,
      "end": 4602961
    },
    {
      "path": "/texlive/texmf-dist/tex/latex/beamer",
      "name": "beamercolorthemerose.sty",
      "start": 4602961,
      "end": 4603804
    },
    {
      "path": "/texlive/texmf-dist/tex/latex/beamer",
      "name": "beamercolorthemeseagull.sty",
      "start": 4603804,
      "end": 4605564
    },
    {
      "path": "/texlive/texmf-dist/tex/latex/beamer",
      "name": "beamercolorthemeseahorse.sty",
      "start": 4605564,
      "end": 4606648
    },
    {
      "path": "/texlive/texmf-dist/tex/latex/beamer",
      "name": "beamercolorthemesidebartab.sty",
      "start": 4606648,
      "end": 4607358
    },
    {
      "path": "/texlive/texmf-dist/tex/latex/beamer",
      "name": "beamercolorthemespruce.sty",
      "start": 4607358,
      "end": 4608823
    },
    {
      "path": "/texlive/texmf-dist/tex/latex/beamer",
      "name": "beamercolorthemestructure.sty",
      "start": 4608823,
      "end": 4609636
    },
    {
      "path": "/texlive/texmf-dist/tex/latex/beamer",
      "name": "beamercolorthemewhale.sty",
      "start": 4609636,
      "end": 4610639
    },
    {
      "path": "/texlive/texmf-dist/tex/latex/beamer",
      "name": "beamercolorthemewolverine.sty",
      "start": 4610639,
      "end": 4611859
    },
    {
      "path": "/texlive/texmf-dist/tex/latex/beamer",
      "name": "beamerfoils.sty",
      "start": 4611859,
      "end": 4613590
    },
    {
      "path": "/texlive/texmf-dist/tex/latex/beamer",
      "name": "beamerfontthemedefault.sty",
      "start": 4613590,
      "end": 4617816
    },
    {
      "path": "/texlive/texmf-dist/tex/latex/beamer",
      "name": "beamerfontthemeprofessionalfonts.sty",
      "start": 4617816,
      "end": 4618139
    },
    {
      "path": "/texlive/texmf-dist/tex/latex/beamer",
      "name": "beamerfontthemeserif.sty",
      "start": 4618139,
      "end": 4619137
    },
    {
      "path": "/texlive/texmf-dist/tex/latex/beamer",
      "name": "beamerfontthemestructurebold.sty",
      "start": 4619137,
      "end": 4619798
    },
    {
      "path": "/texlive/texmf-dist/tex/latex/beamer",
      "name": "beamerfontthemestructureitalicserif.sty",
      "start": 4619798,
      "end": 4620490
    },
    {
      "path": "/texlive/texmf-dist/tex/latex/beamer",
      "name": "beamerfontthemestructuresmallcapsserif.sty",
      "start": 4620490,
      "end": 4621189
    },
    {
      "path": "/texlive/texmf-dist/tex/latex/beamer",
      "name": "beamericonarticle.20.eps",
      "start": 4621189,
      "end": 4638269
    },
    {
      "path": "/texlive/texmf-dist/tex/latex/beamer",
      "name": "beamericonarticle.20.pdf",
      "start": 4638269,
      "end": 4641227
    },
    {
      "path": "/texlive/texmf-dist/tex/latex/beamer",
      "name": "beamericonarticle.eps",
      "start": 4641227,
      "end": 4667830
    },
    {
      "path": "/texlive/texmf-dist/tex/latex/beamer",
      "name": "beamericonarticle.pdf",
      "start": 4667830,
      "end": 4670766
    },
    {
      "path": "/texlive/texmf-dist/tex/latex/beamer",
      "name": "beamericonarticle.tex",
      "start": 4670766,
      "end": 4674220
    },
    {
      "path": "/texlive/texmf-dist/tex/latex/beamer",
      "name": "beamericonbook.20.eps",
      "start": 4674220,
      "end": 4698982
    },
    {
      "path": "/texlive/texmf-dist/tex/latex/beamer",
      "name": "beamericonbook.20.pdf",
      "start": 4698982,
      "end": 4701716
    },
    {
      "path": "/texlive/texmf-dist/tex/latex/beamer",
      "name": "beamericonbook.eps",
      "start": 4701716,
      "end": 4722935
    },
    {
      "path": "/texlive/texmf-dist/tex/latex/beamer",
      "name": "beamericonbook.pdf",
      "start": 4722935,
      "end": 4725602
    },
    {
      "path": "/texlive/texmf-dist/tex/latex/beamer",
      "name": "beamericonbook.tex",
      "start": 4725602,
      "end": 4728641
    },
    {
      "path": "/texlive/texmf-dist/tex/latex/beamer",
      "name": "beamericononline.20.eps",
      "start": 4728641,
      "end": 4761784
    },
    {
      "path": "/texlive/texmf-dist/tex/latex/beamer",
      "name": "beamericononline.20.pdf",
      "start": 4761784,
      "end": 4786235
    },
    {
      "path": "/texlive/texmf-dist/tex/latex/beamer",
      "name": "beamericononline.eps",
      "start": 4786235,
      "end": 4838011
    },
    {
      "path": "/texlive/texmf-dist/tex/latex/beamer",
      "name": "beamericononline.pdf",
      "start": 4838011,
      "end": 4862622
    },
    {
      "path": "/texlive/texmf-dist/tex/latex/beamer",
      "name": "beamerinnerthemecircles.sty",
      "start": 4862622,
      "end": 4863014
    },
    {
      "path": "/texlive/texmf-dist/tex/latex/beamer",
      "name": "beamerinnerthemedefault.sty",
      "start": 4863014,
      "end": 4876794
    },
    {
      "path": "/texlive/texmf-dist/tex/latex/beamer",
      "name": "beamerinnerthemeinmargin.sty",
      "start": 4876794,
      "end": 4881359
    },
    {
      "path": "/texlive/texmf-dist/tex/latex/beamer",
      "name": "beamerinnerthemerectangles.sty",
      "start": 4881359,
      "end": 4881750
    },
    {
      "path": "/texlive/texmf-dist/tex/latex/beamer",
      "name": "beamerinnerthemerounded.sty",
      "start": 4881750,
      "end": 4882752
    },
    {
      "path": "/texlive/texmf-dist/tex/latex/beamer",
      "name": "beamerouterthemedefault.sty",
      "start": 4882752,
      "end": 4889615
    },
    {
      "path": "/texlive/texmf-dist/tex/latex/beamer",
      "name": "beamerouterthemeinfolines.sty",
      "start": 4889615,
      "end": 4891977
    },
    {
      "path": "/texlive/texmf-dist/tex/latex/beamer",
      "name": "beamerouterthememiniframes.sty",
      "start": 4891977,
      "end": 4897134
    },
    {
      "path": "/texlive/texmf-dist/tex/latex/beamer",
      "name": "beamerouterthemeshadow.sty",
      "start": 4897134,
      "end": 4899939
    },
    {
      "path": "/texlive/texmf-dist/tex/latex/beamer",
      "name": "beamerouterthemesidebar.sty",
      "start": 4899939,
      "end": 4905249
    },
    {
      "path": "/texlive/texmf-dist/tex/latex/beamer",
      "name": "beamerouterthemesmoothbars.sty",
      "start": 4905249,
      "end": 4909702
    },
    {
      "path": "/texlive/texmf-dist/tex/latex/beamer",
      "name": "beamerouterthemesmoothtree.sty",
      "start": 4909702,
      "end": 4913693
    },
    {
      "path": "/texlive/texmf-dist/tex/latex/beamer",
      "name": "beamerouterthemesplit.sty",
      "start": 4913693,
      "end": 4916527
    },
    {
      "path": "/texlive/texmf-dist/tex/latex/beamer",
      "name": "beamerouterthemetree.sty",
      "start": 4916527,
      "end": 4918791
    },
    {
      "path": "/texlive/texmf-dist/tex/latex/beamer",
      "name": "beamerpatchparalist.sty",
      "start": 4918791,
      "end": 4924998
    },
    {
      "path": "/texlive/texmf-dist/tex/latex/beamer",
      "name": "beamerprosper.sty",
      "start": 4924998,
      "end": 4930954
    },
    {
      "path": "/texlive/texmf-dist/tex/latex/beamer",
      "name": "beamerseminar.sty",
      "start": 4930954,
      "end": 4932825
    },
    {
      "path": "/texlive/texmf-dist/tex/latex/beamer",
      "name": "beamertexpower.sty",
      "start": 4932825,
      "end": 4934055
    },
    {
      "path": "/texlive/texmf-dist/tex/latex/beamer",
      "name": "beamerthemeAnnArbor.sty",
      "start": 4934055,
      "end": 4934530
    },
    {
      "path": "/texlive/texmf-dist/tex/latex/beamer",
      "name": "beamerthemeAntibes.sty",
      "start": 4934530,
      "end": 4934911
    },
    {
      "path": "/texlive/texmf-dist/tex/latex/beamer",
      "name": "beamerthemebars.sty",
      "start": 4934911,
      "end": 4935334
    },
    {
      "path": "/texlive/texmf-dist/tex/latex/beamer",
      "name": "beamerthemeBergen.sty",
      "start": 4935334,
      "end": 4935702
    },
    {
      "path": "/texlive/texmf-dist/tex/latex/beamer",
      "name": "beamerthemeBerkeley.sty",
      "start": 4935702,
      "end": 4936643
    },
    {
      "path": "/texlive/texmf-dist/tex/latex/beamer",
      "name": "beamerthemeBerlin.sty",
      "start": 4936643,
      "end": 4937137
    },
    {
      "path": "/texlive/texmf-dist/tex/latex/beamer",
      "name": "beamerthemeBoadilla.sty",
      "start": 4937137,
      "end": 4938029
    },
    {
      "path": "/texlive/texmf-dist/tex/latex/beamer",
      "name": "beamerthemeboxes.sty",
      "start": 4938029,
      "end": 4941634
    },
    {
      "path": "/texlive/texmf-dist/tex/latex/beamer",
      "name": "beamerthemeCambridgeUS.sty",
      "start": 4941634,
      "end": 4942095
    },
    {
      "path": "/texlive/texmf-dist/tex/latex/beamer",
      "name": "beamerthemeclassic.sty",
      "start": 4942095,
      "end": 4942516
    },
    {
      "path": "/texlive/texmf-dist/tex/latex/beamer",
      "name": "beamerthemecompatibility.sty",
      "start": 4942516,
      "end": 4943207
    },
    {
      "path": "/texlive/texmf-dist/tex/latex/beamer",
      "name": "beamerthemeCopenhagen.sty",
      "start": 4943207,
      "end": 4943587
    },
    {
      "path": "/texlive/texmf-dist/tex/latex/beamer",
      "name": "beamerthemeDarmstadt.sty",
      "start": 4943587,
      "end": 4943984
    },
    {
      "path": "/texlive/texmf-dist/tex/latex/beamer",
      "name": "beamerthemedefault.sty",
      "start": 4943984,
      "end": 4944329
    },
    {
      "path": "/texlive/texmf-dist/tex/latex/beamer",
      "name": "beamerthemeDresden.sty",
      "start": 4944329,
      "end": 4944781
    },
    {
      "path": "/texlive/texmf-dist/tex/latex/beamer",
      "name": "beamerthemeEastLansing.sty",
      "start": 4944781,
      "end": 4945365
    },
    {
      "path": "/texlive/texmf-dist/tex/latex/beamer",
      "name": "beamerthemeFrankfurt.sty",
      "start": 4945365,
      "end": 4945780
    },
    {
      "path": "/texlive/texmf-dist/tex/latex/beamer",
      "name": "beamerthemeGoettingen.sty",
      "start": 4945780,
      "end": 4946824
    },
    {
      "path": "/texlive/texmf-dist/tex/latex/beamer",
      "name": "beamerthemeHannover.sty",
      "start": 4946824,
      "end": 4947604
    },
    {
      "path": "/texlive/texmf-dist/tex/latex/beamer",
      "name": "beamerthemeIlmenau.sty",
      "start": 4947604,
      "end": 4948095
    },
    {
      "path": "/texlive/texmf-dist/tex/latex/beamer",
      "name": "beamerthemeJuanLesPins.sty",
      "start": 4948095,
      "end": 4948492
    },
    {
      "path": "/texlive/texmf-dist/tex/latex/beamer",
      "name": "beamerthemelined.sty",
      "start": 4948492,
      "end": 4950626
    },
    {
      "path": "/texlive/texmf-dist/tex/latex/beamer",
      "name": "beamerthemeLuebeck.sty",
      "start": 4950626,
      "end": 4951009
    },
    {
      "path": "/texlive/texmf-dist/tex/latex/beamer",
      "name": "beamerthemeMadrid.sty",
      "start": 4951009,
      "end": 4951556
    },
    {
      "path": "/texlive/texmf-dist/tex/latex/beamer",
      "name": "beamerthemeMalmoe.sty",
      "start": 4951556,
      "end": 4951897
    },
    {
      "path": "/texlive/texmf-dist/tex/latex/beamer",
      "name": "beamerthemeMarburg.sty",
      "start": 4951897,
      "end": 4953134
    },
    {
      "path": "/texlive/texmf-dist/tex/latex/beamer",
      "name": "beamerthemeMontpellier.sty",
      "start": 4953134,
      "end": 4953475
    },
    {
      "path": "/texlive/texmf-dist/tex/latex/beamer",
      "name": "beamerthemePaloAlto.sty",
      "start": 4953475,
      "end": 4954424
    },
    {
      "path": "/texlive/texmf-dist/tex/latex/beamer",
      "name": "beamerthemePittsburgh.sty",
      "start": 4954424,
      "end": 4954746
    },
    {
      "path": "/texlive/texmf-dist/tex/latex/beamer",
      "name": "beamerthemeplain.sty",
      "start": 4954746,
      "end": 4955218
    },
    {
      "path": "/texlive/texmf-dist/tex/latex/beamer",
      "name": "beamerthemeRochester.sty",
      "start": 4955218,
      "end": 4955777
    },
    {
      "path": "/texlive/texmf-dist/tex/latex/beamer",
      "name": "beamerthemeshadow.sty",
      "start": 4955777,
      "end": 4956325
    },
    {
      "path": "/texlive/texmf-dist/tex/latex/beamer",
      "name": "beamerthemesidebar.sty",
      "start": 4956325,
      "end": 4957621
    },
    {
      "path": "/texlive/texmf-dist/tex/latex/beamer",
      "name": "beamerthemeSingapore.sty",
      "start": 4957621,
      "end": 4958990
    },
    {
      "path": "/texlive/texmf-dist/tex/latex/beamer",
      "name": "beamerthemesplit.sty",
      "start": 4958990,
      "end": 4959376
    },
    {
      "path": "/texlive/texmf-dist/tex/latex/beamer",
      "name": "beamerthemeSzeged.sty",
      "start": 4959376,
      "end": 4959825
    },
    {
      "path": "/texlive/texmf-dist/tex/latex/beamer",
      "name": "beamerthemetree.sty",
      "start": 4959825,
      "end": 4960395
    },
    {
      "path": "/texlive/texmf-dist/tex/latex/beamer",
      "name": "beamerthemeWarsaw.sty",
      "start": 4960395,
      "end": 4960788
    },
    {
      "path": "/texlive/texmf-dist/tex/latex/beamer",
      "name": "multimedia.sty",
      "start": 4960788,
      "end": 4971321
    },
    {
      "path": "/texlive/texmf-dist/tex/latex/beamer",
      "name": "multimediasymbols.sty",
      "start": 4971321,
      "end": 4972699
    },
    {
      "path": "/texlive/texmf-dist/tex/latex/beamer",
      "name": "xmpmulti.sty",
      "start": 4972699,
      "end": 4979277
    }
  ],
  "totalSize": 4979277
}