{
  "name": "boxes",
  "files": [
    {
      "path": "/texlive/texmf-dist/doc/latex/mdframed",
      "name": "ctan-lion.png",
      "start": 0,
      "end": 81950
    },
    {
      "path": "/texlive/texmf-dist/doc/latex/mdframed",
      "name": "mdframed-example-default.pdf",
      "start": 81950,
      "end": 389254
    },
    {
      "path": "/texlive/texmf-dist/doc/latex/mdframed",
      "name": "mdframed-example-default.tex",
      "start": 389254,
      "end": 397284
    },
    {
      "path": "/texlive/texmf-dist/doc/latex/mdframed",
      "name": "mdframed-example-pstricks.pdf",
      "start": 397284,
      "end": 475629
    },
    {
      "path": "/texlive/texmf-dist/doc/latex/mdframed",
      "name": "mdframed-example-pstricks.tex",
      "start": 475629,
      "end": 480743
    },
    {
      "path": "/texlive/texmf-dist/doc/latex/mdframed",
      "name": "mdframed-example-texsx.pdf",
      "start": 480743,
      "end": 739236
    },
    {
      "path": "/texlive/texmf-dist/doc/latex/mdframed",
      "name": "mdframed-example-texsx.tex",
      "start": 739236,
      "end": 748225
    },
    {
      "path": "/texlive/texmf-dist/doc/latex/mdframed",
      "name": "mdframed-example-tikz.pdf",
      "start": 748225,
      "end": 1075804
    },
    {
      "path": "/texlive/texmf-dist/doc/latex/mdframed",
      "name": "mdframed-example-tikz.tex",
      "start": 1075804,
      "end": 1083122
    },
    {
      "path": "/texlive/texmf-dist/doc/latex/mdframed",
      "name": "mdframed.pdf",
      "start": 1083122,
      "end": 1894428
    },
    {
      "path": "/texlive/texmf-dist/doc/latex/mdframed",
      "name": "README.txt",
      "start": 1894428,
      "end": 1896535
    },
    {
      "path": "/texlive/texmf-dist/doc/latex/tcolorbox",
      "name": "Basilica_5.png",
      "start": 1896535,
      "end": 1918942
    },
    {
      "path": "/texlive/texmf-dist/doc/latex/tcolorbox",
      "name": "CHANGELOG.md",
      "start": 1918942,
      "end": 1999131
    },
    {
      "path": "/texlive/texmf-dist/doc/latex/tcolorbox",
      "name": "lichtspiel.jpg",
      "start": 1999131,
      "end": 2034355
    },
    {
      "path": "/texlive/texmf-dist/doc/latex/tcolorbox",
      "name": "README.md",
      "start": 2034355,
      "end": 2039496
    },
    {
      "path": "/texlive/texmf-dist/doc/latex/tcolorbox",
      "name": "tcolorbox-example-poster.pdf",
      "start": 2039496,
      "end": 2177139
    },
    {
      "path": "/texlive/texmf-dist/doc/latex/tcolorbox",
      "name": "tcolorbox-example-poster.tex",
      "start": 2177139,
      "end": 2183180
    },
    {
      "path": "/texlive/texmf-dist/doc/latex/tcolorbox",
      "name": "tcolorbox-example.pdf",
      "start": 2183180,
      "end": 2470836
    },
    {
      "path": "/texlive/texmf-dist/doc/latex/tcolorbox",
      "name": "tcolorbox-example.tex",
      "start": 2470836,
      "end": 2479187
    },
    {
      "path": "/texlive/texmf-dist/doc/latex/tcolorbox",
      "name": "tcolorbox-tutorial-poster.pdf",
      "start": 2479187,
      "end": 2726196
    },
    {
      "path": "/texlive/texmf-dist/doc/latex/tcolorbox",
      "name": "tcolorbox-tutorial-poster.tex",
      "start": 2726196,
      "end": 2770354
    },
    {
      "path": "/texlive/texmf-dist/doc/latex/tcolorbox",
      "name": "tcolorbox.doc.abstract.tex",
      "start": 2770354,
      "end": 2775813
    },
    {
      "path": "/texlive/texmf-dist/doc/latex/tcolorbox",
      "name": "tcolorbox.doc.beamer.tex",
      "start": 2775813,
      "end": 2784687
    },
    {
      "path": "/texlive/texmf-dist/doc/latex/tcolorbox",
      "name": "tcolorbox.doc.bib",
      "start": 2784687,
      "end": 2791618
    },
    {
      "path": "/texlive/texmf-dist/doc/latex/tcolorbox",
      "name": "tcolorbox.doc.breakable.tex",
      "start": 2791618,
      "end": 2832282
    },
    {
      "path": "/texlive/texmf-dist/doc/latex/tcolorbox",
      "name": "tcolorbox.doc.coremacros.tex",
      "start": 2832282,
      "end": 2854820
    },
    {
      "path": "/texlive/texmf-dist/doc/latex/tcolorbox",
      "name": "tcolorbox.doc.coreoptions.tex",
      "start": 2854820,
      "end": 3041419
    },
    {
      "path": "/texlive/texmf-dist/doc/latex/tcolorbox",
      "name": "tcolorbox.doc.documentation.tex",
      "start": 3041419,
      "end": 3108910
    },
    {
      "path": "/texlive/texmf-dist/doc/latex/tcolorbox",
      "name": "tcolorbox.doc.external.tex",
      "start": 3108910,
      "end": 3134691
    },
    {
      "path": "/texlive/texmf-dist/doc/latex/tcolorbox",
      "name": "tcolorbox.doc.filling.tex",
      "start": 3134691,
      "end": 3139825
    },
    {
      "path": "/texlive/texmf-dist/doc/latex/tcolorbox",
      "name": "tcolorbox.doc.fitting.tex",
      "start": 3139825,
      "end": 3164599
    },
    {
      "path": "/texlive/texmf-dist/doc/latex/tcolorbox",
      "name": "tcolorbox.doc.graphics.tex",
      "start": 3164599,
      "end": 3172584
    },
    {
      "path": "/texlive/texmf-dist/doc/latex/tcolorbox",
      "name": "tcolorbox.doc.hooks.tex",
      "start": 3172584,
      "end": 3202287
    },
    {
      "path": "/texlive/texmf-dist/doc/latex/tcolorbox",
      "name": "tcolorbox.doc.index.tex",
      "start": 3202287,
      "end": 3202399
    },
    {
      "path": "/texlive/texmf-dist/doc/latex/tcolorbox",
      "name": "tcolorbox.doc.initoptions.tex",
      "start": 3202399,
      "end": 3222383
    },
    {
      "path": "/texlive/texmf-dist/doc/latex/tcolorbox",
      "name": "tcolorbox.doc.intro.tex",
      "start": 3222383,
      "end": 3230906
    },
    {
      "path": "/texlive/texmf-dist/doc/latex/tcolorbox",
      "name": "tcolorbox.doc.listings.tex",
      "start": 3230906,
      "end": 3297237
    },
    {
      "path": "/texlive/texmf-dist/doc/latex/tcolorbox",
      "name": "tcolorbox.doc.magazine.tex",
      "start": 3297237,
      "end": 3317507
    },
    {
      "path": "/texlive/texmf-dist/doc/latex/tcolorbox",
      "name": "tcolorbox.doc.picturecredits.tex",
      "start": 3317507,
      "end": 3318613
    },
    {
      "path": "/texlive/texmf-dist/doc/latex/tcolorbox",
      "name": "tcolorbox.doc.poster.tex",
      "start": 3318613,
      "end": 3344189
    },
    {
      "path": "/texlive/texmf-dist/doc/latex/tcolorbox",
      "name": "tcolorbox.doc.quickref.tex",
      "start": 3344189,
      "end": 3349766
    },
    {
      "path": "/texlive/texmf-dist/doc/latex/tcolorbox",
      "name": "tcolorbox.doc.raster.tex",
      "start": 3349766,
      "end": 3382552
    },
    {
      "path": "/texlive/texmf-dist/doc/latex/tcolorbox",
      "name": "tcolorbox.doc.recording.tex",
      "start": 3382552,
      "end": 3388943
    },
    {
      "path": "/texlive/texmf-dist/doc/latex/tcolorbox",
      "name": "tcolorbox.doc.references.tex",
      "start": 3388943,
      "end": 3389091
    },
    {
      "path": "/texlive/texmf-dist/doc/latex/tcolorbox",
      "name": "tcolorbox.doc.s_main.sty",
      "start": 3389091,
      "end": 3401138
    },
    {
      "path": "/texlive/texmf-dist/doc/latex/tcolorbox",
      "name": "tcolorbox.doc.s_snippet.sty",
      "start": 3401138,
      "end": 3407448
    },
    {
      "path": "/texlive/texmf-dist/doc/latex/tcolorbox",
      "name": "tcolorbox.doc.sidebyside.tex",
      "start": 3407448,
      "end": 3421087
    },
    {
      "path": "/texlive/texmf-dist/doc/latex/tcolorbox",
      "name": "tcolorbox.doc.skincatalog.tex",
      "start": 3421087,
      "end": 3477151
    },
    {
      "path": "/texlive/texmf-dist/doc/latex/tcolorbox",
      "name": "tcolorbox.doc.skins.tex",
      "start": 3477151,
      "end": 3590674
    },
    {
      "path": "/texlive/texmf-dist/doc/latex/tcolorbox",
      "name": "tcolorbox.doc.tagging.tex",
      "start": 3590674,
      "end": 3591833
    },
    {
      "path": "/texlive/texmf-dist/doc/latex/tcolorbox",
      "name": "tcolorbox.doc.technical.tex",
      "start": 3591833,
      "end": 3620905
    },
    {
      "path": "/texlive/texmf-dist/doc/latex/tcolorbox",
      "name": "tcolorbox.doc.theorems.tex",
      "start": 3620905,
      "end": 3663530
    },
    {
      "path": "/texlive/texmf-dist/doc/latex/tcolorbox",
      "name": "tcolorbox.doc.verbatim.tex",
      "start": 3663530,
      "end": 3668589
    },
    {
      "path": "/texlive/texmf-dist/doc/latex/tcolorbox",
      "name": "tcolorbox.doc.vignette.tex",
      "start": 3668589,
      "end": 3697030
    },
    {
      "path": "/texlive/texmf-dist/doc/latex/tcolorbox",
      "name": "tcolorbox.doc.xparse.tex",
      "start": 3697030,
      "end": 3698006
    },
    {
      "path": "/texlive/texmf-dist/doc/latex/tcolorbox",
      "name": "tcolorbox.pdf",
      "start": 3698006,
      "end": 8609493
    },
    {
      "path": "/texlive/texmf-dist/doc/latex/tcolorbox",
      "name": "tcolorbox.tex",
      "start": 8609493,
      "end": 8613182
    },
    {
      "path": "/texlive/texmf-dist/source/latex/mdframed",
      "name": "Makefile",
      "start": 8613182,
      "end": 8622661
    },
    {
      "path": "/texlive/texmf-dist/source/latex/mdframed",
      "name": "mdframed.dtx",
      "start": 8622661,
      "end": 8892419
    },
    {
      "path": "/texlive/texmf-dist/source/latex/mdframed",
      "name": "mdframed.ins",
      "start": 8892419,
      "end": 8895814
    },
    {
      "path": "/texlive/texmf-dist/source/latex/mdframed",
      "name": "mdframedmake.bat",
      "start": 8895814,
      "end": 8899133
    },
    {
      "path": "/texlive/texmf-dist/tex/latex/mdframed",
      "name": "ltxmdf.cls",
      "start": 8899133,
      "end": 8915467
    },
    {
      "path": "/texlive/texmf-dist/tex/latex/mdframed",
      "name": "md-frame-0.mdf",
      "start": 8915467,
      "end": 8940298
    },
    {
      "path": "/texlive/texmf-dist/tex/latex/mdframed",
      "name": "md-frame-1.mdf",
      "start": 8940298,
      "end": 8964930
    },
    {
      "path": "/texlive/texmf-dist/tex/latex/mdframed",
      "name": "md-frame-2.mdf",
      "start": 8964930,
      "end": 9005923
    },
    {
      "path": "/texlive/texmf-dist/tex/latex/mdframed",
      "name": "md-frame-3.mdf",
      "start": 9005923,
      "end": 9046916
    },
    {
      "path": "/texlive/texmf-dist/tex/latex/mdframed",
      "name": "mdframed.sty",
      "start": 9046916,
      "end": 9100403
    },
    {
      "path": "/texlive/texmf-dist/tex/latex/tcolorbox",
      "name": "blueshade.png",
      "start": 9100403,
      "end": 9163285
    },
    {
      "path": "/texlive/texmf-dist/tex/latex/tcolorbox",
      "name": "crinklepaper.png",
      "start": 9163285,
      "end": 9184948
    },
    {
      "path": "/texlive/texmf-dist/tex/latex/tcolorbox",
      "name": "goldshade.png",
      "start": 9184948,
      "end": 9261777
    },
    {
      "path": "/texlive/texmf-dist/tex/latex/tcolorbox",
      "name": "pink_marble.png",
      "start": 9261777,
      "end": 9276943
    },
    {
      "path": "/texlive/texmf-dist/tex/latex/tcolorbox",
      "name": "tcbbreakable.code.tex",
      "start": 9276943,
      "end": 9311624
    },
    {
      "path": "/texlive/texmf-dist/tex/latex/tcolorbox",
      "name": "tcbdocumentation.code.tex",
      "start": 9311624,
      "end": 9346073
    },
    {
      "path": "/texlive/texmf-dist/tex/latex/tcolorbox",
      "name": "tcbexternal.code.tex",
      "start": 9346073,
      "end": 9355178
    },
    {
      "path": "/texlive/texmf-dist/tex/latex/tcolorbox",
      "name": "tcbfitting.code.tex",
      "start": 9355178,
      "end": 9372342
    },
    {
      "path": "/texlive/texmf-dist/tex/latex/tcolorbox",
      "name": "tcbhooks.code.tex",
      "start": 9372342,
      "end": 9382715
    },
    {
      "path": "/texlive/texmf-dist/tex/latex/tcolorbox",
      "name": "tcblistings.code.tex",
      "start": 9382715,
      "end": 9386129
    },
    {
      "path": "/texlive/texmf-dist/tex/latex/tcolorbox",
      "name": "tcblistingscore.code.tex",
      "start": 9386129,
      "end": 9402598
    },
    {
      "path": "/texlive/texmf-dist/tex/latex/tcolorbox",
      "name": "tcblistingsutf8.code.tex",
      "start": 9402598,
      "end": 9404012
    },
    {
      "path": "/texlive/texmf-dist/tex/latex/tcolorbox",
      "name": "tcbmagazine.code.tex",
      "start": 9404012,
      "end": 9409648
    },
    {
      "path": "/texlive/texmf-dist/tex/latex/tcolorbox",
      "name": "tcbminted.code.tex",
      "start": 9409648,
      "end": 9413125
    },
    {
      "path": "/texlive/texmf-dist/tex/latex/tcolorbox",
      "name": "tcbposter.code.tex",
      "start": 9413125,
      "end": 9425584
    },
    {
      "path": "/texlive/texmf-dist/tex/latex/tcolorbox",
      "name": "tcbprocessing.code.tex",
      "start": 9425584,
      "end": 9427933
    },
    {
      "path": "/texlive/texmf-dist/tex/latex/tcolorbox",
      "name": "tcbraster.code.tex",
      "start": 9427933,
      "end": 9437277
    },
    {
      "path": "/texlive/texmf-dist/tex/latex/tcolorbox",
      "name": "tcbskins.code.tex",
      "start": 9437277,
      "end": 9522215
    },
    {
      "path": "/texlive/texmf-dist/tex/latex/tcolorbox",
      "name": "tcbskinsjigsaw.code.tex",
      "start": 9522215,
      "end": 9532301
    },
    {
      "path": "/texlive/texmf-dist/tex/latex/tcolorbox",
      "name": "tcbtheorems.code.tex",
      "start": 9532301,
      "end": 9545426
    },
    {
      "path": "/texlive/texmf-dist/tex/latex/tcolorbox",
      "name": "tcbvignette.code.tex",
      "start": 9545426,
      "end": 9558173
    },
    {
      "path": "/texlive/texmf-dist/tex/latex/tcolorbox",
      "name": "tcbxparse.code.tex",
      "start": 9558173,
      "end": 9559154
    },
    {
      "path": "/texlive/texmf-dist/tex/latex/tcolorbox",
      "name": "tcolorbox.sty",
      "start": 9559154,
      "end": 9668061
    }
  ],
  "totalSize": 9668061
}